NuageMetroaeConfig/NuageMetroaeConfig.py
NuageMetroaeConfig/__init__.py
nuage_metroae_config_robot-1.0.1.dist-info/METADATA
nuage_metroae_config_robot-1.0.1.dist-info/WHEEL
nuage_metroae_config_robot-1.0.1.dist-info/top_level.txt
nuage_metroae_config_robot-1.0.1.dist-info/RECORD
