Metadata-Version: 2.1
Name: nuage-metroae-config-robot
Version: 1.0.1
Summary: Library for Nuage MetroAE Config in Robot Framework
Home-page: https://github.com/nuagenetworks/nuage-metroae-config
Author: Nuage Devops
Author-email: devops@nuagenetworks.net
License: UNKNOWN
Platform: UNKNOWN
Classifier: Programming Language :: Python :: 2
Classifier: Programming Language :: Python :: 3
Classifier: License :: OSI Approved :: Apache Software License
Classifier: Operating System :: OS Independent
Requires-Python: >=2.7
Requires-Dist: robotframework
Requires-Dist: nuage-metroae-config
